{"type": "FeatureCollection", "name": "Joined", "features": [{"type": "Feature", "geometry": {"type": "Point", "coordinates": [76.5989229263, 10.5706370913]}, "properties": {"gml_id": "Palakkad_Editor.fid-f0aec0d_192a2341ec3_-592b", "geom": null, "District": "Palakkad", "LSGD": "Nemmara", "Ward_Name": "KOMBANKALLU", "Ward_No": 16, "Lsgd_Type": "Grama Panchayat", "Created_Da": "2024-10-19T10:15:02.599Z", "Surveyor": "shruthi", "Mob_No": "7012608904", "Remarks": "KOMBANKALLU", "Q__result": "PalakkadLocked.Nemmara16", "Q__timesta": "20250528", "_result": "Palakkad_Nemmara", "OBJECTID": 691, "gml_parent_id": null, "gml_parent_property": "featureMembers", "Created_Date": "2024-10-16T13:40:36.564Z", "_ulid": "01JBBD70ZY06YVYKEMQ2YXZT85"}}]}