{"type": "FeatureCollection", "name": "Joined", "features": [{"type": "Feature", "geometry": {"type": "Point", "coordinates": [76.9173143857, 10.0981188849]}, "properties": {"gml_id": "Idukki_Editor.fid-f0aec0d_192a2341ec3_-2ed", "geom": null, "District": "Idukki", "LSGD": "Mankulam", "Ward_Name": "Thalumkandam East", "Ward_No": 9, "Lsgd_Type": "Grama Panchayat", "Created_Da": "2024-10-20T13:43:39.827Z", "Surveyor": "Manoj", "Mob_No": null, "Remarks": "Thalumkandam East", "Q__result": "IdukkiLocked.Mankulam9", "Q__timesta": "20250528", "_result": "Idukki_Mankulam", "OBJECTID": 670, "gml_parent_id": null, "gml_parent_property": "featureMembers", "Created_Date": "2024-10-18T14:37:50.985Z", "_ulid": "01JBBD70ZRNYK3QMTHDEQGSY34"}}]}