{"type": "FeatureCollection", "name": "Joined", "features": [{"type": "Feature", "geometry": {"type": "Point", "coordinates": [76.4144244315, 9.3093168007]}, "properties": {"gml_id": "Alappuzha_Editor.fid-f0aec0d_192a2341ec3_-427e", "geom": null, "District": "Alappuzha", "LSGD": "Karuvatta", "Ward_Name": "SNDPLPS KUNNUTHARA", "Ward_No": 9, "Lsgd_Type": "Grama Panchayat", "Created_Da": "2024-10-19T14:00:31.263Z", "Surveyor": "Kannan T", "Mob_No": "9809833281", "Remarks": "SNDPLPS KUNNUTHARA,NEW WARD", "Q__result": "AlappuzhaLocked.Karuvatta9", "Q__timesta": "20250528", "_result": "Alappuzha_Karuvatta", "OBJECTID": 183, "gml_parent_id": null, "gml_parent_property": "featureMembers", "Created_Date": "2024-10-15T09:04:13.812Z", "_ulid": "01JBBD70T63HDZWYR195FJ6GX8"}}]}