{"type": "FeatureCollection", "name": "Joined", "features": [{"type": "Feature", "geometry": {"type": "Point", "coordinates": [76.8240072456, 8.7295959375]}, "properties": {"gml_id": "Thiruvanathapuram_Editor.fid-f0aec0d_192a2341ec3_3bfe", "geom": null, "District": "Thiruvanathapuram", "LSGD": "Karavaram", "Ward_Name": "Puthiyathadam", "Ward_No": 16, "Lsgd_Type": "Grama Panchayat", "Created_Da": "2024-10-21T13:05:30.941Z", "Surveyor": "Rahul", "Mob_No": "9633651719", "Remarks": "Puthiyathadam", "Q__result": "ThiruvanathapuramLocked.Karavaram16", "Q__timesta": "20250528", "_result": "Thiruvanathapuram_Karavaram", "OBJECTID": 756, "gml_parent_id": null, "gml_parent_property": "featureMembers", "Created_Date": "2024-10-22T09:18:25.849Z", "_ulid": "01JBBD710K9ZQYDSYB7M65YNYY"}}, {"type": "Feature", "geometry": {"type": "Point", "coordinates": [76.8291956765, 8.7288206082]}, "properties": {"gml_id": "Thiruvanathapuram_Editor.fid-f0aec0d_192a2341ec3_2c98", "geom": null, "District": "Thiruvanathapuram", "LSGD": "Karavaram", "Ward_Name": "Mevarkal", "Ward_No": 15, "Lsgd_Type": "Grama Panchayat", "Created_Da": "2024-10-21T10:31:25.137Z", "Surveyor": "Rahul", "Mob_No": "9633651719", "Remarks": "Mevarkal", "Q__result": "ThiruvanathapuramLocked.Karavaram15", "Q__timesta": "20250528", "_result": "Thiruvanathapuram_Karavaram", "OBJECTID": 756, "gml_parent_id": null, "gml_parent_property": "featureMembers", "Created_Date": "2024-10-22T09:18:25.849Z", "_ulid": "01JBBD710K9ZQYDSYB7M65YNYY"}}]}